psmpar/__init__.py
psmpar/bgc.py
psmpar/blast.py
psmpar/default.py
psmpar/main.py
psmpar/model.py
psmpar/seqkit.py
psmpar/utils.py
psmpar-0.0.1.data/scripts/psmpar
psmpar-0.0.1.dist-info/LICENSE
psmpar-0.0.1.dist-info/METADATA
psmpar-0.0.1.dist-info/WHEEL
psmpar-0.0.1.dist-info/top_level.txt
psmpar-0.0.1.dist-info/RECORD
